tickr_client/__init__.py
tickr_client/client.py
tickr_client-0.1.2.dist-info/licenses/LICENSE
tickr_client-0.1.2.dist-info/METADATA
tickr_client-0.1.2.dist-info/WHEEL
tickr_client-0.1.2.dist-info/top_level.txt
tickr_client-0.1.2.dist-info/RECORD
