Metadata-Version: 2.4
Name: tickr-client
Version: 0.1.2
Summary: Python client for the Tickr API (counters service)
Author-email: DavidMChan <david@iridescent.io>
Maintainer-email: DavidMChan <david@iridescent.io>
License: Copyright 2025 David Chan
Project-URL: Homepage, https://tickr.cc
Project-URL: Repository, https://github.com/DavidMChan/tickr-client
Project-URL: Issues, https://github.com/DavidMChan/tickr-client/issues
Keywords: api,client,tickr,counters,supabase
Classifier: Development Status :: 3 - Alpha
Classifier: Intended Audience :: Developers
Classifier: License :: OSI Approved :: MIT License
Classifier: Programming Language :: Python :: 3
Classifier: Programming Language :: Python :: 3.7
Classifier: Programming Language :: Python :: 3.8
Classifier: Programming Language :: Python :: 3.9
Classifier: Programming Language :: Python :: 3.10
Classifier: Programming Language :: Python :: 3.11
Classifier: Programming Language :: Python :: 3.12
Requires-Python: >=3.7
License-File: LICENSE
Requires-Dist: requests>=2.25.1
Dynamic: license-file
